[
    {
        "created_time": "1501598575", 
        "days_since_posting": 1.428, 
        "follow_ratio": 0.38436348751535, 
        "follows": 939, 
        "likes": 803, 
        "meanLikes": 458.1604938271605, 
        "tags": [
            "person", 
            "woman", 
            "outdoor", 
            "others_", 
            "outdoor_", 
            "people_show"
        ]
    }, 
    {
        "created_time": "1500160275", 
        "days_since_posting": 18.075, 
        "follow_ratio": 0.38436348751535, 
        "follows": 939, 
        "likes": 776, 
        "meanLikes": 458.1604938271605, 
        "tags": [
            "outdoor", 
            "building", 
            "car", 
            "road", 
            "street", 
            "building_", 
            "others_", 
            "outdoor_"
        ]
    }, 
    {
        "created_time": "1500064561", 
        "days_since_posting": 19.183, 
        "follow_ratio": 0.38436348751535, 
        "follows": 939, 
        "likes": 826, 
        "meanLikes": 458.1604938271605, 
        "tags": [
            "tree", 
            "outdoor", 
            "abstract_", 
            "others_", 
            "outdoor_"
        ]
    }, 
    {
        "created_time": "1499991826", 
        "days_since_posting": 20.025, 
        "follow_ratio": 0.38436348751535, 
        "follows": 939, 
        "likes": 755, 
        "meanLikes": 458.1604938271605, 
        "tags": [
            "outdoor", 
            "tree", 
            "water", 
            "nature", 
            "person", 
            "river", 
            "outdoor_", 
            "plant_tree"
        ]
    }, 
    {
        "created_time": "1497279970", 
        "days_since_posting": 51.412, 
        "follow_ratio": 0.38436348751535, 
        "follows": 939, 
        "likes": 958, 
        "meanLikes": 458.1604938271605, 
        "tags": [
            "person", 
            "outdoor", 
            "ground", 
            "people_"
        ]
    }, 
    {
        "created_time": "1497193261", 
        "days_since_posting": 52.416, 
        "follow_ratio": 0.38436348751535, 
        "follows": 939, 
        "likes": 867, 
        "meanLikes": 458.1604938271605, 
        "tags": [
            "person", 
            "wall", 
            "woman", 
            "indoor", 
            "people_"
        ]
    }, 
    {
        "created_time": "1496535013", 
        "days_since_posting": 60.034, 
        "follow_ratio": 0.38436348751535, 
        "follows": 939, 
        "likes": 949, 
        "meanLikes": 458.1604938271605, 
        "tags": [
            "outdoor", 
            "person", 
            "woman", 
            "clothing", 
            "posing", 
            "people_group"
        ]
    }, 
    {
        "created_time": "1496439221", 
        "days_since_posting": 61.143, 
        "follow_ratio": 0.38436348751535, 
        "follows": 939, 
        "likes": 1023, 
        "meanLikes": 458.1604938271605, 
        "tags": [
            "water", 
            "indoor", 
            "person", 
            "plate", 
            "others_", 
            "outdoor_"
        ]
    }, 
    {
        "created_time": "1496180520", 
        "days_since_posting": 64.137, 
        "follow_ratio": 0.38436348751535, 
        "follows": 939, 
        "likes": 624, 
        "meanLikes": 458.1604938271605, 
        "tags": [
            "outdoor", 
            "sky", 
            "person", 
            "sky_cloud"
        ]
    }, 
    {
        "created_time": "1495930635", 
        "days_since_posting": 67.029, 
        "follow_ratio": 0.38436348751535, 
        "follows": 939, 
        "likes": 762, 
        "meanLikes": 458.1604938271605, 
        "tags": [
            "person", 
            "woman", 
            "indoor", 
            "others_", 
            "outdoor_"
        ]
    }
]