[
    {
        "created_time": "1502452257", 
        "days_since_posting": 0.612, 
        "follow_ratio": 1.529175050301811, 
        "followed_by": 1520, 
        "follows": 994, 
        "likes": 55, 
        "meanLikes": 94.92957746478874, 
        "postID": "1579006435895115360_13420887", 
        "tags": [
            "person", 
            "indoor", 
            "people_"
        ]
    }, 
    {
        "created_time": "1502413023", 
        "days_since_posting": 1.066, 
        "follow_ratio": 1.529175050301811, 
        "followed_by": 1520, 
        "follows": 994, 
        "likes": 125, 
        "meanLikes": 94.92957746478874, 
        "postID": "1578677322986586201_13420887", 
        "tags": [
            "person", 
            "indoor", 
            "people_portrait"
        ]
    }, 
    {
        "created_time": "1502228657", 
        "days_since_posting": 3.2, 
        "follow_ratio": 1.529175050301811, 
        "followed_by": 1520, 
        "follows": 994, 
        "likes": 45, 
        "meanLikes": 94.92957746478874, 
        "postID": "1577130742919758516_13420887", 
        "tags": [
            "boy", 
            "young", 
            "child", 
            "little", 
            "others_", 
            "people_"
        ]
    }, 
    {
        "created_time": "1502153691", 
        "days_since_posting": 4.068, 
        "follow_ratio": 1.529175050301811, 
        "followed_by": 1520, 
        "follows": 994, 
        "likes": 130, 
        "meanLikes": 94.92957746478874, 
        "postID": "1576501886827498075_13420887", 
        "tags": [
            "person", 
            "others_"
        ]
    }, 
    {
        "created_time": "1502024682", 
        "days_since_posting": 5.561, 
        "follow_ratio": 1.529175050301811, 
        "followed_by": 1520, 
        "follows": 994, 
        "likes": 41, 
        "meanLikes": 94.92957746478874, 
        "postID": "1575419677467021408_13420887", 
        "tags": [
            "person", 
            "outdoor", 
            "people_"
        ]
    }, 
    {
        "created_time": "1501848792", 
        "days_since_posting": 7.597, 
        "follow_ratio": 1.529175050301811, 
        "followed_by": 1520, 
        "follows": 994, 
        "likes": 80, 
        "meanLikes": 94.92957746478874, 
        "postID": "1573944206665453031_13420887", 
        "tags": [
            "person", 
            "ground", 
            "outdoor", 
            "little", 
            "young", 
            "people_"
        ]
    }, 
    {
        "created_time": "1501803320", 
        "days_since_posting": 8.123, 
        "follow_ratio": 1.529175050301811, 
        "followed_by": 1520, 
        "follows": 994, 
        "likes": 33, 
        "meanLikes": 94.92957746478874, 
        "postID": "1573562761317162444_13420887", 
        "tags": [
            "person", 
            "indoor", 
            "people_portrait"
        ]
    }, 
    {
        "created_time": "1501688028", 
        "days_since_posting": 9.458, 
        "follow_ratio": 1.529175050301811, 
        "followed_by": 1520, 
        "follows": 994, 
        "likes": 35, 
        "meanLikes": 94.92957746478874, 
        "postID": "1572595622686837094_13420887", 
        "tags": [
            "water", 
            "sky", 
            "outdoor", 
            "ocean", 
            "nature", 
            "outdoor_", 
            "outdoor_waterside"
        ]
    }, 
    {
        "created_time": "1501685969", 
        "days_since_posting": 9.482, 
        "follow_ratio": 1.529175050301811, 
        "followed_by": 1520, 
        "follows": 994, 
        "likes": 192, 
        "meanLikes": 94.92957746478874, 
        "postID": "1572578351004510962_13420887", 
        "tags": [
            "person", 
            "others_", 
            "people_"
        ]
    }, 
    {
        "created_time": "1501359796", 
        "days_since_posting": 13.257, 
        "follow_ratio": 1.529175050301811, 
        "followed_by": 1520, 
        "follows": 994, 
        "likes": 116, 
        "meanLikes": 94.92957746478874, 
        "postID": "1569842208064310930_13420887", 
        "tags": [
            "person", 
            "indoor", 
            "people_young"
        ]
    }
]